corevolution/__init__.py
corevolution/helper.py
corevolution/linalg.py
corevolution/data_types/__init__.py
corevolution/data_types/array.py
corevolution/warp/__init__.py
corevolution-0.1.0.dist-info/LICENSE
corevolution-0.1.0.dist-info/METADATA
corevolution-0.1.0.dist-info/WHEEL
corevolution-0.1.0.dist-info/top_level.txt
corevolution-0.1.0.dist-info/RECORD
